LICENSE
MANIFEST.in
README.md
requirements.txt
setup.py
docs/api.rst
docs/conf.py
docs/index.rst
docs/_media/logo.png
docs/_templates/python/module.rst
docs/_templates/python/package.rst
stocksml/__init__.py
stocksml/data.py
stocksml/model.py
stocksml/trade.py
stocksml.egg-info/PKG-INFO
stocksml.egg-info/SOURCES.txt
stocksml.egg-info/dependency_links.txt
stocksml.egg-info/requires.txt
stocksml.egg-info/top_level.txt
stocksml/data/BND.csv
stocksml/data/SPY.csv
stocksml/data/VIXM.csv
stocksml/data/VNQI.csv